{
  "stops": [
    {
      "hour" : 9,
      "minutes": "0-30",
      "name" : "Tokyo",
      "country" : "Japon",
      "lat" : 35.6845,
      "long" : 139.7577,
      "time_zone": 0,
      "code": "0",
	  "message": ""
    },
    {
      "hour" : 9,
      "minutes": "31-59",
      "name" : "Pek&iacute;n",
      "country" : "China",
      "lat" : 34.525143,
      "long" : 86.013458,
      "time_zone": 0,
      "code": "0",
	  "message": ""
    },
    {
      "hour" : 10,
      "minutes": "0-45",
      "name" : "Rusia",
      "country" : "Rusia",
      "lat" : 22.880357,
      "long" : -82.018741,
      "time_zone": 0,
      "code": "0",
	  "message": ""
    },
    {
      "hour" : 10,
      "minutes": "46-59",
      "name" : "Polonia",
      "country" : "Polonia",
      "lat" : 51.8402565,
      "long" : -14.64649,
      "time_zone": 0,
      "code": "0",
	  "message": ""
    },
    {
      "hour" : 11,
      "minutes": "0-30",
      "name" : "Alemania",
      "country" : "Alemania",
      "lat" : 50.7688441,
      "long" : 8.2304743,
      "time_zone": 0,
      "code": "0",
	  "message": ""
    },
    {
      "hour" : 11,
      "minutes": "31-59",
      "name" : "Suiza",
      "country" : "Suiza",
      "lat" : 48.2148625,
      "long" : 6.077154,
      "time_zone": 0,
      "code": "0",
	  "message": ""
    },
    {
      "hour" : 12,
      "minutes": "0-30",
      "name" : "Francia",
      "country" : "Francia",
      "lat" : 45.8777618,
      "long" : -6.7773685,
      "time_zone": 0,
      "code": "0",
	  "message": ""
    },
    {
      "hour" : 12,
      "minutes": "31-59",
      "name" : "Italia",
      "country" : "Italia",
      "lat" : 40.9576498,
      "long" : 3.5747673,
      "time_zone": 0,
      "code": "0",
	  "message": ""
    },
    {
      "hour" : 13,
      "minutes": "0-30",
      "name" : "Madrid",
      "country" : "Espa&ntilde;a",
      "lat" : 39.8757545,
      "long" : -12.7145881,
      "time_zone": 0,
      "code": "0",
	  "message": ""
    },
    {
      "hour" : 14,
      "minutes": "31-59",
      "name" : "Inglaterra",
      "country" : "Reino Unido",
      "lat" : 39.8757545,
      "long" : -12.7145881,
      "time_zone": 0,
      "code": "0",
	  "message": ""
    },
    {
      "hour" : 15,
      "minutes": "0-30",
      "name" : "Groenlandia",
      "country" : "Groenlandia",
      "lat" : 61.4938353,
      "long" : -55.1075416,
      "time_zone": 0,
      "code": "0",
	  "message": ""
    },
    {
      "hour" : 16,
      "minutes": "31-59",
      "name" : "Toronto",
      "country" : "Canad&aacute;",
      "lat" : 50.8464613,
      "long" : -130.235056,
      "time_zone": 0,
      "code": "0",
	  "message": ""
    },
    {
      "hour" : 17,
      "minutes": "0-30",
      "name" : "Michigan",
      "country" : "USA",
      "lat" : 44.8632388,
      "long" : -90.9065791,
      "time_zone": 0,
      "code": "0",
	  "message": ""
    },
    {
      "hour" : 17,
      "minutes": "31-59",
      "name" : "Illinois",
      "country" : "USA",
      "lat" : 39.6611311,
      "long" : -93.9969731,
      "time_zone": 0,
      "code": "0",
	  "message": ""
    },
    {
      "hour" : 18,
      "minutes": "0-30",
      "name" : "Kentucky",
      "country" : "USA",
      "lat" : 37.8053491,
      "long" : -88.0122994,
      "time_zone": 0,
      "code": "0",
	  "message": ""
    },
    {
      "hour" : 18,
      "minutes": "31-59",
      "name" : "Carolina del Norte",
      "country" : "USA",
      "lat" : 35.1981563,
      "long" : -82.1354637,
      "time_zone": 0,
      "code": "0",
	  "message": ""
    },
    {
      "hour" : 19,
      "minutes": "0-30",
      "name" : "Carolina del Sur",
      "country" : "USA",
      "lat" : 33.6092884,
      "long" : -83.1913434,
      "time_zone": 0,
      "code": "0",
	  "message": ""
    },
    {
      "hour" : 19,
      "minutes": "31-59",
      "name" : "Georgia",
      "country" : "USA",
      "lat" : 32.6627763,
      "long" : -85.4676136,
      "time_zone": 0,
      "code": "0",
	  "message": ""
    },
    {
      "hour" : 20,
      "minutes": "0-30",
      "name" : "Orlando Florida",
      "country" : "USA",
      "lat" : 28.4813989,
      "long" : -81.5088382,
      "time_zone": 0,
      "code": "0",
	  "message": ""
    },
    {
      "hour" : 20,
      "minutes": "31-59",
      "name" : "Tampa Florida",
      "country" : "USA",
      "lat" : 33.6092884,
      "long" : -83.1913434,
      "time_zone": 0,
      "code": "0",
	  "message": ""
    },
    {
      "hour" : 21,
      "minutes": "0-30",
      "name" : "Miami Beach",
      "country" : "USA",
      "lat" : 25.814092,
      "long" : -80.2143476,
      "time_zone": 0,
      "code": "0",
	  "message": ""
    },
    {
      "hour" : 21,
      "minutes": "31-59",
      "name" : "Miami Florida",
      "country" : "USA",
      "lat" : 25.7824618,
      "long" : -80.3010444,
      "time_zone": 0,
      "code": "0",
	  "message": ""
    },
    {
      "hour" : 22,
      "minutes": "0-4",
      "name" : "PINAR_DEL_RIO",
      "country" : "Cuba",
      "lat" : 22.41632,
      "long" : -83.69823,
      "time_zone": 4,
      "code": "PR",
	  "message": ""
    },
    {
      "hour" : 22,
      "minutes": "5-8",
      "name" : "ARTEMISA",
      "country" : "Cuba",
      "lat" : 22.81352,
      "long" : -82.75798,
      "time_zone": 4,
      "code": "A",
	  "message": ""
    },
    {
      "hour" : 22,
      "minutes": "9-12",
      "name" : "MAYABEQUE",
      "country" : "Cuba",
      "lat" : 22.83619,
      "long" : -82.02811,
      "time_zone": 4,
      "code": "MY",
	  "message": ""
    },
    {
      "hour" : 22,
      "minutes": "13-16",
      "name" : "LA_HABANA",
      "country" : "Cuba",
      "lat" : 23.113593,
      "long" : -82.366596,
      "time_zone": 4,
      "code": "LH",
	  "message": ""
    },
    {
      "hour" : 22,
      "minutes": "17-20",
      "name" : "MATANZAS",
      "country" : "Cuba",
      "lat" : 22.71684,
      "long" : -80.90607,
      "time_zone": 4,
      "code": "M",
	  "message": ""
    },
    {
      "hour" : 22,
      "minutes": "21-24",
      "name" : "CIENFUEGOS",
      "country" : "Cuba",
      "lat" : 22.14859,
      "long" : -80.44557,
      "time_zone": 4,
      "code": "CF",
	  "message": ""
    },
    {
      "hour" : 22,
      "minutes": "25-28",
      "name" : "VILLA_CLARA",
      "country" : "Cuba",
      "lat" : 22.40597,
      "long" : -79.96545,
      "time_zone": 4,
      "code": "VC",
	  "message": ""
    },
    {
      "hour" : 22,
      "minutes": "33-36",
      "name" : "SANCTI_SPIRITUS",
      "country" : "Cuba",
      "lat" : 21.925,
      "long" : -79.44192,
      "time_zone": 4,
      "code": "SS",
	  "message": ""
    },
    {
      "hour" : 22,
      "minutes": "29-32",
      "name" : "CIEGO_DE_AVILA",
      "country" : "Cuba",
      "lat" : 21.84202,
      "long" : -78.76,
      "time_zone": 4,
      "code": "CA",
	  "message": ""
    },
    {
      "hour" : 22,
      "minutes": "37-40",
      "name" : "CAMAG&#154;EY",
      "country" : "Cuba",
      "lat" : 21.37702,
      "long" : -77.91352,
      "time_zone": 4,
      "code": "C",
	  "message": ""
    },
    {
      "hour" : 22,
      "minutes": "41-44",
      "name" : "LAS_TUNAS",
      "country" : "Cuba",
      "lat" : 20.95641,
      "long" : -76.95402,
      "time_zone": 4,
      "code": "LT",
	  "message": ""
    },
    {
      "hour" : 22,
      "minutes": "45-48",
      "name" : "HOLGUIN",
      "country" : "Cuba",
      "lat" : 20.896610,
      "long" : -76.262497,
      "time_zone": 4,
      "code": "HO",
	  "message": ""
    },
    {
      "hour" : 22,
      "minutes": "49-52",
      "name" : "GRANMA",
      "country" : "Cuba",
      "lat" : 20.37949,
      "long" : -76.64286,
      "time_zone": 4,
      "code": "GR",
	  "message": ""
    },
    {
      "hour" : 22,
      "minutes": "53-56",
      "name" : "SANTIAGO_DE_CUBA",
      "country" : "Cuba",
      "lat" : 20.22259,
      "long" : -76.00016,
      "time_zone": 4,
      "code": "SC",
	  "message": ""
    },
    {
      "hour" : 22,
      "minutes": "57-59",
      "name" : "GUANTANAMO",
      "country" : "Cuba",
      "lat" : 20.14291,
      "long" : -75.20353,
      "time_zone": 4,
      "code": "G",
	  "message": ""
    },
    {
      "hour" : 23,
      "minutes": "0-4",
      "name" : "ISLA_DE_LA_JUVENTUD",
      "country" : "Cuba",
      "lat" : 21.88431,
      "long" : -82.80408,
      "time_zone": 4,
      "code": "IJ",
	  "message": ""
    }
  ]
}